{"index.md":"4d753573","posts_algorithm-2048.md":"71969988","posts_ascii-art.md":"3b71fb5d","posts_calc-demo.md":"889aab68","posts_call-cpp-from-python.md":"60688746","posts_cpp-promise.md":"35aae88d","posts_d3-note.md":"66f83092","posts_fix-matplotlib-chinese.md":"9e1e1f1b","posts_indexeddb.md":"b533d193","posts_love2d-require-c-library.md":"a0299e7b","posts_new-to-arch.md":"f2d685ca","posts_pattern-recognition-note.md":"09aff844","posts_pyside2-quick-start.md":"5e414e6c","posts_python-opencv.md":"10926210","posts_ripple-animation.md":"6b5278b5","posts_rust-list-slice.md":"5ea5df1f","posts_tensorflow-note.md":"e549cc04","posts_tetris-field-compress.md":"37534f1a","posts_write-code-from-answer.md":"32feeb58","posts_xjb-utils.md":"753ac4ff","readme.md":"14caf4ef","tags_index.md":"8b3bd39e"}
